sealwatch-2025.9.dist-info/METADATA
sealwatch-2025.9.dist-info/WHEEL
sealwatch-2025.9.dist-info/licenses/LICENSE
sealwatch/F5/__init__.py
sealwatch/F5/_attack.py
sealwatch/__init__.py
sealwatch/_sealwatch.abi3.so
sealwatch/chi2/__init__.py
sealwatch/chi2/_attack.py
sealwatch/dctr/__init__.py
sealwatch/dctr/_dctr.py
sealwatch/ensemble_classifier/__init__.py
sealwatch/ensemble_classifier/base_learner.py
sealwatch/ensemble_classifier/ensemble_classifier.py
sealwatch/ensemble_classifier/fld.py
sealwatch/ensemble_classifier/fld_ensemble_trainer.py
sealwatch/ensemble_classifier/helpers.py
sealwatch/ensemble_classifier/out_of_bag_error_estimates.py
sealwatch/ensemble_classifier/subspace_dimensionality_search.py
sealwatch/gfr/__init__.py
sealwatch/gfr/_gfr.py
sealwatch/hcfcom/__init__.py
sealwatch/hcfcom/hcfcom.py
sealwatch/jrm/__init__.py
sealwatch/jrm/absolute_value_features.py
sealwatch/jrm/ccjrm.py
sealwatch/jrm/common.py
sealwatch/jrm/cooccurrence.py
sealwatch/jrm/difference_features.py
sealwatch/jrm/integral_features.py
sealwatch/jrm/jrm.md
sealwatch/jrm/jrm.py
sealwatch/jrm/symmetrization.py
sealwatch/pharm/__init__.py
sealwatch/pharm/pharm_original.py
sealwatch/pharm/pharm_revisited.py
sealwatch/rjca/__init__.py
sealwatch/rjca/_attack.py
sealwatch/spa/__init__.py
sealwatch/spa/_attack.py
sealwatch/spam/__init__.py
sealwatch/spam/spam.py
sealwatch/srm/__init__.py
sealwatch/srm/cooccurrence.py
sealwatch/srm/crm.py
sealwatch/srm/srm.py
sealwatch/srm/srmq1.py
sealwatch/srm/symm.py
sealwatch/tools/__init__.py
sealwatch/tools/_backend.py
sealwatch/tools/_defs.py
sealwatch/tools/calibration.py
sealwatch/tools/dct.py
sealwatch/tools/features.py
sealwatch/tools/jpeg.py
sealwatch/tools/matlab.py
sealwatch/tools/networks.py
sealwatch/tools/signal.py
sealwatch/ws/__init__.py
sealwatch/ws/_attack.py
sealwatch/ws/_unet.py
sealwatch/xunet/__init__.py
sealwatch/xunet/_xunet.py
sealwatch-2025.9.dist-info/RECORD
