Metadata-Version: 2.4
Name: sealwatch
Version: 2025.9
Classifier: Development Status :: 3 - Alpha
Classifier: Intended Audience :: Science/Research
Classifier: Intended Audience :: Developers
Classifier: Intended Audience :: Education
Classifier: Intended Audience :: Information Technology
Classifier: Intended Audience :: Other Audience
Classifier: License :: OSI Approved :: Mozilla Public License 2.0 (MPL 2.0)
Classifier: Programming Language :: Python
Classifier: Programming Language :: Python :: 3
Classifier: Topic :: Communications
Classifier: Topic :: Education
Classifier: Topic :: Multimedia
Classifier: Topic :: Multimedia :: Graphics
Classifier: Topic :: Scientific/Engineering
Classifier: Topic :: Scientific/Engineering :: Image Processing
Classifier: Topic :: Security
Classifier: Topic :: Utilities
Requires-Dist: numpy
Requires-Dist: scipy
Requires-Dist: jpeglib
Requires-Dist: h5py
Requires-Dist: pandas
Requires-Dist: pillow
Requires-Dist: torch
Requires-Dist: torchvision
Requires-Dist: tqdm
Requires-Dist: flake8 ; extra == 'dev'
Requires-Dist: parameterized ; extra == 'dev'
Requires-Dist: conseal ; extra == 'dev'
Requires-Dist: scikit-learn ; extra == 'dev'
Requires-Dist: maturin ; extra == 'dev'
Provides-Extra: dev
Provides-Extra: deploy
License-File: LICENSE
Summary: Implementation of modern image steganalysis algorithms
Keywords: steganalysis,image,jpeg
Author-email: Martin Benes <martin.benes@uibk.ac.at>, Benedikt Lorch <benedikt.lorch@uibk.ac.at>
Requires-Python: >=3.8
Project-URL: Homepage, https://pypi.org/project/sealwatch/
Project-URL: Documentation, https://sealwatch.readthedocs.io/
Project-URL: Source, https://github.com/uibk-uncover/sealwatch/
